txt2dub/__init__.py
txt2dub/__main__.py
txt2dub/app.py
txt2dub/models/__init__.py
txt2dub/models/base.py
txt2dub/models/script.py
txt2dub/screens/__init__.py
txt2dub/screens/file/__init__.py
txt2dub/screens/file/screen.py
txt2dub/screens/file/widgets.py
txt2dub/screens/script/__init__.py
txt2dub/screens/script/messages.py
txt2dub/screens/script/screen.py
txt2dub/screens/script/widgets.py
txt2dub/services/__init__.py
txt2dub/services/actions.py
txt2dub/services/tts.py
txt2dub/styles/app.css
txt2dub/tts/__init__.py
txt2dub/tts/__main__.py
txt2dub/tts/interpreter.py
txt2dub/widgets/__init__.py
txt2dub/widgets/base.py
txt2dub/widgets/logo.py
txt2dub-0.1.3.dist-info/LICENSE
txt2dub-0.1.3.dist-info/METADATA
txt2dub-0.1.3.dist-info/WHEEL
txt2dub-0.1.3.dist-info/entry_points.txt
txt2dub-0.1.3.dist-info/RECORD
