Metadata-Version: 2.1
Name: txt2dub
Version: 0.1.3
Summary: A text-based UI application for editing voiceover scripts and generating text to speech performances.
Home-page: https://github.com/NotYourDadsMath/txt2dub
License: MIT
Author: Mike Kibbel
Requires-Python: >=3.7,<4.0
Classifier: License :: OSI Approved :: MIT License
Classifier: Programming Language :: Python :: 3
Classifier: Programming Language :: Python :: 3.7
Classifier: Programming Language :: Python :: 3.8
Classifier: Programming Language :: Python :: 3.9
Classifier: Programming Language :: Python :: 3.10
Classifier: Programming Language :: Python :: 3.11
Requires-Dist: pyobjc (==9.0.1) ; sys_platform == "darwin"
Requires-Dist: pyttsx3-alt (>=2.91,<3.0)
Requires-Dist: textual (>=0.26.0,<0.27.0)
